risus/__init__.py
risus/__main__.py
risus/damage_policy.py
risus/dice.py
risus/engine.py
risus/table.py
risus_py-0.1.1.dist-info/LICENSE
risus_py-0.1.1.dist-info/METADATA
risus_py-0.1.1.dist-info/WHEEL
risus_py-0.1.1.dist-info/top_level.txt
risus_py-0.1.1.dist-info/RECORD
