Metadata-Version: 2.1
Name: risus-py
Version: 0.1.1
Summary: Compute outcome probabilities for Risus: The Anything RPG
Author-email: "Preston M. Firestone" <firestone.preston@gmail.com>
License: GPLv3+
Project-URL: Repository, https://git.sr.ht/~p0mf/risus-py
Classifier: License :: OSI Approved :: GNU General Public License v3 or later (GPLv3+)
Classifier: Development Status :: 3 - Alpha
Classifier: Topic :: Games/Entertainment :: Role-Playing
License-File: LICENSE
Requires-Dist: icepool
Requires-Dist: xarray
